{
  "Searchdir": [
    "adl/exer"
  ],
  "Outputdir": "out",
  "MergeAdlext": "",
  "Debug": true,
  "NoGoFmt": false,
  "GoAdlPath": "github.com/adl-lang/goadl_rt/v3",
  "ModulePath": "",
  "GoModFile": "",
  "ExcludeAst": false,
  "ModuleMap": [
    {
      "ModuleName": "sys.adlast",
      "Name": "adlast",
      "Path": "github.com/adl-lang/goadl_rt/v3/sys/adlast"
    },
    {
      "ModuleName": "sys.types",
      "Name": "types",
      "Path": "github.com/adl-lang/goadl_rt/v3/sys/types"
    }
  ],
  "GenAstInfo": [],
  "StdLibGen": false,
  "Files": [
    "adl/exer/exer02/simple_struct.adl"
  ]
}
